cryptit/__init__.py
cryptit/__version__.py
cryptit/cli.py
cryptit-0.1.6.dist-info/DESCRIPTION.rst
cryptit-0.1.6.dist-info/METADATA
cryptit-0.1.6.dist-info/RECORD
cryptit-0.1.6.dist-info/WHEEL
cryptit-0.1.6.dist-info/entry_points.txt
cryptit-0.1.6.dist-info/metadata.json
cryptit-0.1.6.dist-info/top_level.txt
cryptit-0.1.6.dist-info/zip-safe
