Metadata-Version: 2.0
Name: cryptit
Version: 0.1.6
Summary: Encryption has never been so easy!
Home-page: https://github.com/KKStudLab/cryptit/
Author: Maxim Krivich
Author-email: maxkrivich@gmail.com
License: MIT
Keywords: encryption,encrypting-files,aes-encryption,aes-256,aes-256-cbc,sha3-256,decryption,file-protector,encryption-tool
Platform: UNKNOWN
Classifier: Natural Language :: English
Classifier: Intended Audience :: End Users/Desktop
Classifier: License :: OSI Approved :: MIT License
Classifier: Topic :: Security :: Cryptography
Classifier: Operating System :: MacOS :: MacOS X
Classifier: Operating System :: Microsoft :: Windows
Classifier: Operating System :: Unix
Classifier: Programming Language :: Python :: 2
Classifier: Programming Language :: Python :: 2.7
Classifier: Programming Language :: Python :: 3
Classifier: Programming Language :: Python :: 3.2
Classifier: Programming Language :: Python :: 3.3
Classifier: Programming Language :: Python :: 3.4
Classifier: Programming Language :: Python :: 3.5
Classifier: Programming Language :: Python :: 3.6
Requires-Dist: pycryptodome (==3.4.7)
Requires-Dist: tqdm (==4.15.0)
